wgconfig/__init__.py
wgconfig/wgexec.py
wgconfig-1.1.0.dist-info/LICENSE
wgconfig-1.1.0.dist-info/METADATA
wgconfig-1.1.0.dist-info/WHEEL
wgconfig-1.1.0.dist-info/top_level.txt
wgconfig-1.1.0.dist-info/RECORD
