Metadata-Version: 2.2
Name: wgconfig
Version: 1.1.0
Summary: parsing and writing WireGuard configuration files
Home-page: https://www.github.com/towalink/wgconfig
Author: Dirk Henrici
Author-email: towalink.wgconfig@henrici.name
Project-URL: Repository, https://www.github.com/towalink/wgconfig
Project-URL: PyPi, https://pypi.org/project/wgconfig/
Keywords: WireGuard configuration config wg
Classifier: Programming Language :: Python
Classifier: License :: OSI Approved :: GNU Affero General Public License v3 or later (AGPLv3+)
Classifier: Operating System :: POSIX :: Linux
Classifier: Development Status :: 5 - Production/Stable
Classifier: Intended Audience :: System Administrators
Classifier: Intended Audience :: Developers
Classifier: Intended Audience :: Information Technology
Requires-Python: >=2.7
License-File: LICENSE
Requires-Dist: future; python_version == "2.7"
Dynamic: author
Dynamic: author-email
Dynamic: classifier
Dynamic: description
Dynamic: description-content-type
Dynamic: home-page
Dynamic: keywords
Dynamic: project-url
Dynamic: provides-extra
Dynamic: requires-python
Dynamic: summary
